[
  {
    "id": 1001,
    "limit_island_well_id": 1001,
    "grade": 1,
    "battle_id": 530000001
  },
  {
    "id": 1002,
    "limit_island_well_id": 1002,
    "grade": 1,
    "battle_id": 530000004
  },
  {
    "id": 1003,
    "limit_island_well_id": 1003,
    "grade": 1,
    "battle_id": 530000013
  },
  {
    "id": 1004,
    "limit_island_well_id": 1001,
    "grade": 2,
    "battle_id": 530000002
  },
  {
    "id": 1005,
    "limit_island_well_id": 1002,
    "grade": 2,
    "battle_id": 530000005
  },
  {
    "id": 1006,
    "limit_island_well_id": 1003,
    "grade": 2,
    "battle_id": 530000014
  },
  {
    "id": 1007,
    "limit_island_well_id": 1004,
    "grade": 1,
    "battle_id": 530010001
  },
  {
    "id": 1008,
    "limit_island_well_id": 1005,
    "grade": 1,
    "battle_id": 530010002
  },
  {
    "id": 1009,
    "limit_island_well_id": 1006,
    "grade": 1,
    "battle_id": 530010003
  },
  {
    "id": 1010,
    "limit_island_well_id": 1004,
    "grade": 2,
    "battle_id": 530010004
  },
  {
    "id": 1011,
    "limit_island_well_id": 1005,
    "grade": 2,
    "battle_id": 530010005
  },
  {
    "id": 1012,
    "limit_island_well_id": 1006,
    "grade": 2,
    "battle_id": 530010006
  },
  {
    "id": 1013,
    "limit_island_well_id": 1007,
    "grade": 1,
    "battle_id": 530020001
  },
  {
    "id": 1014,
    "limit_island_well_id": 1007,
    "grade": 2,
    "battle_id": 530020002
  },
  {
    "id": 1015,
    "limit_island_well_id": 1008,
    "grade": 1,
    "battle_id": 530020004
  },
  {
    "id": 1016,
    "limit_island_well_id": 1008,
    "grade": 2,
    "battle_id": 530020005
  },
  {
    "id": 1017,
    "limit_island_well_id": 1009,
    "grade": 1,
    "battle_id": 530020007
  },
  {
    "id": 1018,
    "limit_island_well_id": 1009,
    "grade": 2,
    "battle_id": 530020008
  },
  {
    "id": 1019,
    "limit_island_well_id": 1011,
    "grade": 1,
    "battle_id": 530030001
  },
  {
    "id": 1020,
    "limit_island_well_id": 1011,
    "grade": 2,
    "battle_id": 530030004
  },
  {
    "id": 1021,
    "limit_island_well_id": 1010,
    "grade": 1,
    "battle_id": 530030002
  },
  {
    "id": 1022,
    "limit_island_well_id": 1010,
    "grade": 2,
    "battle_id": 530030005
  },
  {
    "id": 1023,
    "limit_island_well_id": 1012,
    "grade": 1,
    "battle_id": 530030003
  },
  {
    "id": 1024,
    "limit_island_well_id": 1012,
    "grade": 2,
    "battle_id": 530030006
  },
  {
    "id": 1025,
    "limit_island_well_id": 1011,
    "grade": 3,
    "battle_id": 530030007
  },
  {
    "id": 1026,
    "limit_island_well_id": 1010,
    "grade": 3,
    "battle_id": 530030008
  },
  {
    "id": 1027,
    "limit_island_well_id": 1012,
    "grade": 3,
    "battle_id": 530030009
  },
  {
    "id": 1037,
    "limit_island_well_id": 1016,
    "grade": 1,
    "battle_id": 530050001
  },
  {
    "id": 1038,
    "limit_island_well_id": 1016,
    "grade": 2,
    "battle_id": 530050004
  },
  {
    "id": 1039,
    "limit_island_well_id": 1016,
    "grade": 3,
    "battle_id": 530050007
  },
  {
    "id": 1040,
    "limit_island_well_id": 1017,
    "grade": 1,
    "battle_id": 530050002
  },
  {
    "id": 1041,
    "limit_island_well_id": 1017,
    "grade": 2,
    "battle_id": 530050005
  },
  {
    "id": 1042,
    "limit_island_well_id": 1017,
    "grade": 3,
    "battle_id": 530050008
  },
  {
    "id": 1043,
    "limit_island_well_id": 1018,
    "grade": 1,
    "battle_id": 530000001
  },
  {
    "id": 1044,
    "limit_island_well_id": 1018,
    "grade": 2,
    "battle_id": 530000002
  },
  {
    "id": 1045,
    "limit_island_well_id": 1018,
    "grade": 3,
    "battle_id": 530000003
  },
  {
    "id": 1046,
    "limit_island_well_id": 1019,
    "grade": 1,
    "battle_id": 530010001
  },
  {
    "id": 1047,
    "limit_island_well_id": 1019,
    "grade": 2,
    "battle_id": 530010004
  },
  {
    "id": 1048,
    "limit_island_well_id": 1019,
    "grade": 3,
    "battle_id": 530010007
  },
  {
    "id": 1049,
    "limit_island_well_id": 1020,
    "grade": 1,
    "battle_id": 530010002
  },
  {
    "id": 1050,
    "limit_island_well_id": 1020,
    "grade": 2,
    "battle_id": 530010005
  },
  {
    "id": 1051,
    "limit_island_well_id": 1020,
    "grade": 3,
    "battle_id": 530010008
  },
  {
    "id": 1052,
    "limit_island_well_id": 1021,
    "grade": 1,
    "battle_id": 530010003
  },
  {
    "id": 1053,
    "limit_island_well_id": 1021,
    "grade": 2,
    "battle_id": 530010006
  },
  {
    "id": 1054,
    "limit_island_well_id": 1021,
    "grade": 3,
    "battle_id": 530010009
  }
]